[{"path":"src/main/java/Deadline.java","fileType":"java","lines":[{"lineNumber":1,"author":{"gitId":"kevinkuo0320"},"content":"public class Deadline extends Task {","lastModifiedDate":"2022-01-20"},{"lineNumber":2,"author":{"gitId":"kevinkuo0320"},"content":"    public String tag;","lastModifiedDate":"2022-01-20"},{"lineNumber":3,"author":{"gitId":"kevinkuo0320"},"content":"    public String time;","lastModifiedDate":"2022-01-20"},{"lineNumber":4,"author":{"gitId":"kevinkuo0320"},"content":"","lastModifiedDate":"2022-01-20"},{"lineNumber":5,"author":{"gitId":"kevinkuo0320"},"content":"    public Deadline(String description, String time){","lastModifiedDate":"2022-01-20"},{"lineNumber":6,"author":{"gitId":"kevinkuo0320"},"content":"        super(description, \"D\");","lastModifiedDate":"2022-01-20"},{"lineNumber":7,"author":{"gitId":"kevinkuo0320"},"content":"        this.tag \u003d \"D\";","lastModifiedDate":"2022-01-20"},{"lineNumber":8,"author":{"gitId":"kevinkuo0320"},"content":"        this.time \u003d time;","lastModifiedDate":"2022-01-20"},{"lineNumber":9,"author":{"gitId":"kevinkuo0320"},"content":"    }","lastModifiedDate":"2022-01-20"},{"lineNumber":10,"author":{"gitId":"kevinkuo0320"},"content":"","lastModifiedDate":"2022-01-20"},{"lineNumber":11,"author":{"gitId":"kevinkuo0320"},"content":"    public String getTag(){","lastModifiedDate":"2022-01-20"},{"lineNumber":12,"author":{"gitId":"kevinkuo0320"},"content":"        return \"[\" + tag + \"]\";","lastModifiedDate":"2022-01-20"},{"lineNumber":13,"author":{"gitId":"kevinkuo0320"},"content":"    }","lastModifiedDate":"2022-01-20"},{"lineNumber":14,"author":{"gitId":"kevinkuo0320"},"content":"    public String getTime(){","lastModifiedDate":"2022-01-20"},{"lineNumber":15,"author":{"gitId":"kevinkuo0320"},"content":"        return \"(by: \" + time + \")\";","lastModifiedDate":"2022-01-20"},{"lineNumber":16,"author":{"gitId":"kevinkuo0320"},"content":"    }","lastModifiedDate":"2022-01-20"},{"lineNumber":17,"author":{"gitId":"kevinkuo0320"},"content":"}","lastModifiedDate":"2022-01-20"}],"authorContributionMap":{"kevinkuo0320":17}},{"path":"src/main/java/Duke.java","fileType":"java","lines":[{"lineNumber":1,"author":{"gitId":"kevinkuo0320"},"content":"import java.util.Scanner;","lastModifiedDate":"2022-01-20"},{"lineNumber":2,"author":{"gitId":"kevinkuo0320"},"content":"","lastModifiedDate":"2022-01-20"},{"lineNumber":3,"author":{"gitId":"kevinkuo0320"},"content":"","lastModifiedDate":"2022-01-20"},{"lineNumber":4,"author":{"gitId":"-"},"content":"public class Duke {","lastModifiedDate":"2019-07-29"},{"lineNumber":5,"author":{"gitId":"kevinkuo0320"},"content":"","lastModifiedDate":"2022-01-20"},{"lineNumber":6,"author":{"gitId":"kevinkuo0320"},"content":"    public static Task[] strArray \u003d new Task[100];","lastModifiedDate":"2022-01-20"},{"lineNumber":7,"author":{"gitId":"kevinkuo0320"},"content":"    public static int index \u003d 0;","lastModifiedDate":"2022-01-20"},{"lineNumber":8,"author":{"gitId":"kevinkuo0320"},"content":"","lastModifiedDate":"2022-01-20"},{"lineNumber":9,"author":{"gitId":"kevinkuo0320"},"content":"","lastModifiedDate":"2022-01-20"},{"lineNumber":10,"author":{"gitId":"kevinkuo0320"},"content":"    public static void main(String[] args) throws DukeException {","lastModifiedDate":"2022-01-20"},{"lineNumber":11,"author":{"gitId":"kevinkuo0320"},"content":"","lastModifiedDate":"2022-01-20"},{"lineNumber":12,"author":{"gitId":"kevinkuo0320"},"content":"        System.out.println(\"hello im duke wassup \\n what can I help you?\");","lastModifiedDate":"2022-01-20"},{"lineNumber":13,"author":{"gitId":"kevinkuo0320"},"content":"        Scanner sc \u003d new Scanner(System.in);","lastModifiedDate":"2022-01-20"},{"lineNumber":14,"author":{"gitId":"kevinkuo0320"},"content":"        String echo \u003d sc.nextLine();","lastModifiedDate":"2022-01-20"},{"lineNumber":15,"author":{"gitId":"kevinkuo0320"},"content":"        while(!echo.equals( \"bye\") ){","lastModifiedDate":"2022-01-20"},{"lineNumber":16,"author":{"gitId":"kevinkuo0320"},"content":"            if(echo.equals(\"list\")){","lastModifiedDate":"2022-01-20"},{"lineNumber":17,"author":{"gitId":"kevinkuo0320"},"content":"                for(int i \u003d 0; i \u003c index; i++){","lastModifiedDate":"2022-01-20"},{"lineNumber":18,"author":{"gitId":"kevinkuo0320"},"content":"                    int num \u003d i + 1;","lastModifiedDate":"2022-01-20"},{"lineNumber":19,"author":{"gitId":"kevinkuo0320"},"content":"                    String status \u003d strArray[i].getStatus();","lastModifiedDate":"2022-01-20"},{"lineNumber":20,"author":{"gitId":"kevinkuo0320"},"content":"                    String tag \u003d strArray[i].getTag();","lastModifiedDate":"2022-01-20"},{"lineNumber":21,"author":{"gitId":"kevinkuo0320"},"content":"                    System.out.println(\"here are the stuffs in your list: \");","lastModifiedDate":"2022-01-20"},{"lineNumber":22,"author":{"gitId":"kevinkuo0320"},"content":"                    System.out.println(num + status + strArray[i]);","lastModifiedDate":"2022-01-20"},{"lineNumber":23,"author":{"gitId":"kevinkuo0320"},"content":"                    System.out.println(\"Now you have \" + Duke.index + \" tasks in your list\");","lastModifiedDate":"2022-01-20"},{"lineNumber":24,"author":{"gitId":"kevinkuo0320"},"content":"                }","lastModifiedDate":"2022-01-20"},{"lineNumber":25,"author":{"gitId":"kevinkuo0320"},"content":"            } else if(echo.substring(0,4).equals(\"mark\")){","lastModifiedDate":"2022-01-20"},{"lineNumber":26,"author":{"gitId":"kevinkuo0320"},"content":"                int index \u003d Integer.parseInt(echo.substring(echo.length()-1));","lastModifiedDate":"2022-01-20"},{"lineNumber":27,"author":{"gitId":"kevinkuo0320"},"content":"                strArray[index - 1].changeStatus();","lastModifiedDate":"2022-01-20"},{"lineNumber":28,"author":{"gitId":"kevinkuo0320"},"content":"                System.out.println(\"I have marked: \" +","lastModifiedDate":"2022-01-20"},{"lineNumber":29,"author":{"gitId":"kevinkuo0320"},"content":"                         strArray[index - 1].getStatus()  + strArray[index - 1] );","lastModifiedDate":"2022-01-20"},{"lineNumber":30,"author":{"gitId":"kevinkuo0320"},"content":"            } else if(echo.substring(0,6).equals(\"unmark\")){","lastModifiedDate":"2022-01-20"},{"lineNumber":31,"author":{"gitId":"kevinkuo0320"},"content":"                int index \u003d Integer.parseInt(echo.substring(echo.length()-1));","lastModifiedDate":"2022-01-20"},{"lineNumber":32,"author":{"gitId":"kevinkuo0320"},"content":"                strArray[index - 1].changeStatus();","lastModifiedDate":"2022-01-20"},{"lineNumber":33,"author":{"gitId":"kevinkuo0320"},"content":"                System.out.println(\"I have unmarked: \" +","lastModifiedDate":"2022-01-20"},{"lineNumber":34,"author":{"gitId":"kevinkuo0320"},"content":"                         strArray[index - 1].getStatus()  + strArray[index - 1] );","lastModifiedDate":"2022-01-20"},{"lineNumber":35,"author":{"gitId":"kevinkuo0320"},"content":"            } else if(echo.substring(0,4).equals(\"todo\")) {","lastModifiedDate":"2022-01-20"},{"lineNumber":36,"author":{"gitId":"kevinkuo0320"},"content":"                if(echo.equals(\"todo\")){","lastModifiedDate":"2022-01-20"},{"lineNumber":37,"author":{"gitId":"kevinkuo0320"},"content":"                    System.out.println(\"wrong\");","lastModifiedDate":"2022-01-20"},{"lineNumber":38,"author":{"gitId":"kevinkuo0320"},"content":"                    //throw new DukeException(echo);","lastModifiedDate":"2022-01-20"},{"lineNumber":39,"author":{"gitId":"kevinkuo0320"},"content":"","lastModifiedDate":"2022-01-20"},{"lineNumber":40,"author":{"gitId":"kevinkuo0320"},"content":"                } else {","lastModifiedDate":"2022-01-20"},{"lineNumber":41,"author":{"gitId":"kevinkuo0320"},"content":"                    Todo t \u003d new Todo(echo);","lastModifiedDate":"2022-01-20"},{"lineNumber":42,"author":{"gitId":"kevinkuo0320"},"content":"                    strArray[index] \u003d t;","lastModifiedDate":"2022-01-20"},{"lineNumber":43,"author":{"gitId":"kevinkuo0320"},"content":"                    System.out.println(\"ok i have added this task: \");","lastModifiedDate":"2022-01-20"},{"lineNumber":44,"author":{"gitId":"kevinkuo0320"},"content":"                    System.out.println(t.getTag() + t.getStatus() + \" \" + echo);","lastModifiedDate":"2022-01-20"},{"lineNumber":45,"author":{"gitId":"kevinkuo0320"},"content":"                    index++;","lastModifiedDate":"2022-01-20"},{"lineNumber":46,"author":{"gitId":"kevinkuo0320"},"content":"                }","lastModifiedDate":"2022-01-20"},{"lineNumber":47,"author":{"gitId":"kevinkuo0320"},"content":"            }","lastModifiedDate":"2022-01-20"},{"lineNumber":48,"author":{"gitId":"kevinkuo0320"},"content":"            else if(echo.substring(0,8).equals(\"deadline\")){","lastModifiedDate":"2022-01-20"},{"lineNumber":49,"author":{"gitId":"kevinkuo0320"},"content":"                String time \u003d echo.substring(echo.lastIndexOf(\"/\") + 1);","lastModifiedDate":"2022-01-20"},{"lineNumber":50,"author":{"gitId":"kevinkuo0320"},"content":"                Deadline t \u003d new Deadline(echo, time);","lastModifiedDate":"2022-01-20"},{"lineNumber":51,"author":{"gitId":"kevinkuo0320"},"content":"                strArray[index] \u003d t;","lastModifiedDate":"2022-01-20"},{"lineNumber":52,"author":{"gitId":"kevinkuo0320"},"content":"                System.out.println(\"ok i have added this task: \");","lastModifiedDate":"2022-01-20"},{"lineNumber":53,"author":{"gitId":"kevinkuo0320"},"content":"                System.out.println(t.getTag() + t.getStatus() + t + \" by \" + t.time);","lastModifiedDate":"2022-01-20"},{"lineNumber":54,"author":{"gitId":"kevinkuo0320"},"content":"                index++;","lastModifiedDate":"2022-01-20"},{"lineNumber":55,"author":{"gitId":"kevinkuo0320"},"content":"            } else if(echo.substring(0,5).equals(\"event\")) {","lastModifiedDate":"2022-01-20"},{"lineNumber":56,"author":{"gitId":"kevinkuo0320"},"content":"                String time \u003decho.substring(echo.lastIndexOf(\"/\") + 1);","lastModifiedDate":"2022-01-20"},{"lineNumber":57,"author":{"gitId":"kevinkuo0320"},"content":"                Event t \u003d new Event(echo, time);","lastModifiedDate":"2022-01-20"},{"lineNumber":58,"author":{"gitId":"kevinkuo0320"},"content":"                strArray[index] \u003d t;","lastModifiedDate":"2022-01-20"},{"lineNumber":59,"author":{"gitId":"kevinkuo0320"},"content":"                System.out.println(\"ok i have added this task: \");","lastModifiedDate":"2022-01-20"},{"lineNumber":60,"author":{"gitId":"kevinkuo0320"},"content":"                System.out.println(t.getTag() + t.getStatus() + \"at\" + t.getTime());","lastModifiedDate":"2022-01-20"},{"lineNumber":61,"author":{"gitId":"kevinkuo0320"},"content":"                index++;","lastModifiedDate":"2022-01-20"},{"lineNumber":62,"author":{"gitId":"kevinkuo0320"},"content":"            } else if (echo.substring(0,6).equals(\"delete\")) {","lastModifiedDate":"2022-01-20"},{"lineNumber":63,"author":{"gitId":"kevinkuo0320"},"content":"                int deleteIndex \u003d Integer.parseInt(echo.substring(echo.length() - 1));","lastModifiedDate":"2022-01-20"},{"lineNumber":64,"author":{"gitId":"kevinkuo0320"},"content":"                Task deleteTask \u003d strArray[deleteIndex - 1];","lastModifiedDate":"2022-01-20"},{"lineNumber":65,"author":{"gitId":"kevinkuo0320"},"content":"                removeTask(deleteIndex, strArray);","lastModifiedDate":"2022-01-20"},{"lineNumber":66,"author":{"gitId":"kevinkuo0320"},"content":"                System.out.println(\"ok i have removed\" + deleteTask.toString());","lastModifiedDate":"2022-01-20"},{"lineNumber":67,"author":{"gitId":"kevinkuo0320"},"content":"            }","lastModifiedDate":"2022-01-20"},{"lineNumber":68,"author":{"gitId":"kevinkuo0320"},"content":"            else {","lastModifiedDate":"2022-01-20"},{"lineNumber":69,"author":{"gitId":"kevinkuo0320"},"content":"                System.out.println(\"I dont understand what that means!!\");","lastModifiedDate":"2022-01-20"},{"lineNumber":70,"author":{"gitId":"kevinkuo0320"},"content":"            }","lastModifiedDate":"2022-01-20"},{"lineNumber":71,"author":{"gitId":"kevinkuo0320"},"content":"            echo \u003d sc.nextLine();","lastModifiedDate":"2022-01-20"},{"lineNumber":72,"author":{"gitId":"-"},"content":"        }","lastModifiedDate":"2019-07-29"},{"lineNumber":73,"author":{"gitId":"kevinkuo0320"},"content":"","lastModifiedDate":"2022-01-20"},{"lineNumber":74,"author":{"gitId":"kevinkuo0320"},"content":"        System.out.println(\"byebye see u!\");","lastModifiedDate":"2022-01-20"},{"lineNumber":75,"author":{"gitId":"kevinkuo0320"},"content":"        sc.close();","lastModifiedDate":"2022-01-20"},{"lineNumber":76,"author":{"gitId":"-"},"content":"    }","lastModifiedDate":"2022-01-20"},{"lineNumber":77,"author":{"gitId":"kevinkuo0320"},"content":"","lastModifiedDate":"2022-01-20"},{"lineNumber":78,"author":{"gitId":"kevinkuo0320"},"content":"    public static void removeTask(int deleteIndex, Task[] array){","lastModifiedDate":"2022-01-20"},{"lineNumber":79,"author":{"gitId":"kevinkuo0320"},"content":"        Task[] copy \u003d new Task[array.length - 1];","lastModifiedDate":"2022-01-20"},{"lineNumber":80,"author":{"gitId":"kevinkuo0320"},"content":"","lastModifiedDate":"2022-01-20"},{"lineNumber":81,"author":{"gitId":"kevinkuo0320"},"content":"        for (int i \u003d 0, j \u003d 0; i \u003c array.length; i++) {","lastModifiedDate":"2022-01-20"},{"lineNumber":82,"author":{"gitId":"kevinkuo0320"},"content":"            if (i !\u003d index) {","lastModifiedDate":"2022-01-20"},{"lineNumber":83,"author":{"gitId":"kevinkuo0320"},"content":"                copy[j++] \u003d array[i];","lastModifiedDate":"2022-01-20"},{"lineNumber":84,"author":{"gitId":"kevinkuo0320"},"content":"            }","lastModifiedDate":"2022-01-20"},{"lineNumber":85,"author":{"gitId":"kevinkuo0320"},"content":"        }","lastModifiedDate":"2022-01-20"},{"lineNumber":86,"author":{"gitId":"kevinkuo0320"},"content":"        strArray \u003d copy;","lastModifiedDate":"2022-01-20"},{"lineNumber":87,"author":{"gitId":"kevinkuo0320"},"content":"    }","lastModifiedDate":"2022-01-20"},{"lineNumber":88,"author":{"gitId":"kevinkuo0320"},"content":"","lastModifiedDate":"2022-01-20"},{"lineNumber":89,"author":{"gitId":"kevinkuo0320"},"content":"","lastModifiedDate":"2022-01-20"},{"lineNumber":90,"author":{"gitId":"kevinkuo0320"},"content":"","lastModifiedDate":"2022-01-20"},{"lineNumber":91,"author":{"gitId":"-"},"content":"}","lastModifiedDate":"2019-07-29"}],"authorContributionMap":{"kevinkuo0320":87,"-":4}},{"path":"src/main/java/DukeException.java","fileType":"java","lines":[{"lineNumber":1,"author":{"gitId":"kevinkuo0320"},"content":"public class DukeException extends Exception{","lastModifiedDate":"2022-01-20"},{"lineNumber":2,"author":{"gitId":"kevinkuo0320"},"content":"    public DukeException(String errMessage){","lastModifiedDate":"2022-01-20"},{"lineNumber":3,"author":{"gitId":"kevinkuo0320"},"content":"        super(errMessage);","lastModifiedDate":"2022-01-20"},{"lineNumber":4,"author":{"gitId":"kevinkuo0320"},"content":"    }","lastModifiedDate":"2022-01-20"},{"lineNumber":5,"author":{"gitId":"kevinkuo0320"},"content":"","lastModifiedDate":"2022-01-20"},{"lineNumber":6,"author":{"gitId":"kevinkuo0320"},"content":"    @Override","lastModifiedDate":"2022-01-20"},{"lineNumber":7,"author":{"gitId":"kevinkuo0320"},"content":"    public String getMessage(){","lastModifiedDate":"2022-01-20"},{"lineNumber":8,"author":{"gitId":"kevinkuo0320"},"content":"        return \"i dont understand what you mean!\";","lastModifiedDate":"2022-01-20"},{"lineNumber":9,"author":{"gitId":"kevinkuo0320"},"content":"    }","lastModifiedDate":"2022-01-20"},{"lineNumber":10,"author":{"gitId":"kevinkuo0320"},"content":"","lastModifiedDate":"2022-01-20"},{"lineNumber":11,"author":{"gitId":"kevinkuo0320"},"content":"}","lastModifiedDate":"2022-01-20"}],"authorContributionMap":{"kevinkuo0320":11}},{"path":"src/main/java/Event.java","fileType":"java","lines":[{"lineNumber":1,"author":{"gitId":"kevinkuo0320"},"content":"public class Event extends Task{","lastModifiedDate":"2022-01-20"},{"lineNumber":2,"author":{"gitId":"kevinkuo0320"},"content":"    public String tag;","lastModifiedDate":"2022-01-20"},{"lineNumber":3,"author":{"gitId":"kevinkuo0320"},"content":"    public String time;","lastModifiedDate":"2022-01-20"},{"lineNumber":4,"author":{"gitId":"kevinkuo0320"},"content":"","lastModifiedDate":"2022-01-20"},{"lineNumber":5,"author":{"gitId":"kevinkuo0320"},"content":"    public Event(String description, String time){","lastModifiedDate":"2022-01-20"},{"lineNumber":6,"author":{"gitId":"kevinkuo0320"},"content":"        super(description, \"E\");","lastModifiedDate":"2022-01-20"},{"lineNumber":7,"author":{"gitId":"kevinkuo0320"},"content":"        this.tag \u003d \"E\";","lastModifiedDate":"2022-01-20"},{"lineNumber":8,"author":{"gitId":"kevinkuo0320"},"content":"        this.time \u003d time;","lastModifiedDate":"2022-01-20"},{"lineNumber":9,"author":{"gitId":"kevinkuo0320"},"content":"    }","lastModifiedDate":"2022-01-20"},{"lineNumber":10,"author":{"gitId":"kevinkuo0320"},"content":"","lastModifiedDate":"2022-01-20"},{"lineNumber":11,"author":{"gitId":"kevinkuo0320"},"content":"    @Override","lastModifiedDate":"2022-01-20"},{"lineNumber":12,"author":{"gitId":"kevinkuo0320"},"content":"    public String getTag(){","lastModifiedDate":"2022-01-20"},{"lineNumber":13,"author":{"gitId":"kevinkuo0320"},"content":"        return \"[\" + tag + \"]\";","lastModifiedDate":"2022-01-20"},{"lineNumber":14,"author":{"gitId":"kevinkuo0320"},"content":"    }","lastModifiedDate":"2022-01-20"},{"lineNumber":15,"author":{"gitId":"kevinkuo0320"},"content":"","lastModifiedDate":"2022-01-20"},{"lineNumber":16,"author":{"gitId":"kevinkuo0320"},"content":"    public String getTime(){","lastModifiedDate":"2022-01-20"},{"lineNumber":17,"author":{"gitId":"kevinkuo0320"},"content":"        return \"(at: \" + time + \")\";","lastModifiedDate":"2022-01-20"},{"lineNumber":18,"author":{"gitId":"kevinkuo0320"},"content":"    }","lastModifiedDate":"2022-01-20"},{"lineNumber":19,"author":{"gitId":"kevinkuo0320"},"content":"","lastModifiedDate":"2022-01-20"},{"lineNumber":20,"author":{"gitId":"kevinkuo0320"},"content":"}","lastModifiedDate":"2022-01-20"}],"authorContributionMap":{"kevinkuo0320":20}},{"path":"src/main/java/Task.java","fileType":"java","lines":[{"lineNumber":1,"author":{"gitId":"kevinkuo0320"},"content":"public abstract class Task {","lastModifiedDate":"2022-01-20"},{"lineNumber":2,"author":{"gitId":"kevinkuo0320"},"content":"    String Description;","lastModifiedDate":"2022-01-20"},{"lineNumber":3,"author":{"gitId":"kevinkuo0320"},"content":"    boolean isDone;","lastModifiedDate":"2022-01-20"},{"lineNumber":4,"author":{"gitId":"kevinkuo0320"},"content":"    String tag;","lastModifiedDate":"2022-01-20"},{"lineNumber":5,"author":{"gitId":"kevinkuo0320"},"content":"","lastModifiedDate":"2022-01-20"},{"lineNumber":6,"author":{"gitId":"kevinkuo0320"},"content":"    public Task (String Description, String tag){","lastModifiedDate":"2022-01-20"},{"lineNumber":7,"author":{"gitId":"kevinkuo0320"},"content":"        this.Description \u003d Description;","lastModifiedDate":"2022-01-20"},{"lineNumber":8,"author":{"gitId":"kevinkuo0320"},"content":"        this.isDone \u003d false;","lastModifiedDate":"2022-01-20"},{"lineNumber":9,"author":{"gitId":"kevinkuo0320"},"content":"        this.tag \u003d tag;","lastModifiedDate":"2022-01-20"},{"lineNumber":10,"author":{"gitId":"kevinkuo0320"},"content":"    }","lastModifiedDate":"2022-01-20"},{"lineNumber":11,"author":{"gitId":"kevinkuo0320"},"content":"    public void changeStatus(){","lastModifiedDate":"2022-01-20"},{"lineNumber":12,"author":{"gitId":"kevinkuo0320"},"content":"        this.isDone \u003d !isDone;","lastModifiedDate":"2022-01-20"},{"lineNumber":13,"author":{"gitId":"kevinkuo0320"},"content":"    }","lastModifiedDate":"2022-01-20"},{"lineNumber":14,"author":{"gitId":"kevinkuo0320"},"content":"","lastModifiedDate":"2022-01-20"},{"lineNumber":15,"author":{"gitId":"kevinkuo0320"},"content":"    public String getStatus(){","lastModifiedDate":"2022-01-20"},{"lineNumber":16,"author":{"gitId":"kevinkuo0320"},"content":"        if(this.isDone){","lastModifiedDate":"2022-01-20"},{"lineNumber":17,"author":{"gitId":"kevinkuo0320"},"content":"            return \"[X]\";","lastModifiedDate":"2022-01-20"},{"lineNumber":18,"author":{"gitId":"kevinkuo0320"},"content":"        } else {","lastModifiedDate":"2022-01-20"},{"lineNumber":19,"author":{"gitId":"kevinkuo0320"},"content":"            return \"[]\";","lastModifiedDate":"2022-01-20"},{"lineNumber":20,"author":{"gitId":"kevinkuo0320"},"content":"        }","lastModifiedDate":"2022-01-20"},{"lineNumber":21,"author":{"gitId":"kevinkuo0320"},"content":"    }","lastModifiedDate":"2022-01-20"},{"lineNumber":22,"author":{"gitId":"kevinkuo0320"},"content":"    @Override","lastModifiedDate":"2022-01-20"},{"lineNumber":23,"author":{"gitId":"kevinkuo0320"},"content":"    public String toString(){","lastModifiedDate":"2022-01-20"},{"lineNumber":24,"author":{"gitId":"kevinkuo0320"},"content":"        return Description;","lastModifiedDate":"2022-01-20"},{"lineNumber":25,"author":{"gitId":"kevinkuo0320"},"content":"    }","lastModifiedDate":"2022-01-20"},{"lineNumber":26,"author":{"gitId":"kevinkuo0320"},"content":"","lastModifiedDate":"2022-01-20"},{"lineNumber":27,"author":{"gitId":"kevinkuo0320"},"content":"    public String getTag(){","lastModifiedDate":"2022-01-20"},{"lineNumber":28,"author":{"gitId":"kevinkuo0320"},"content":"        return tag;","lastModifiedDate":"2022-01-20"},{"lineNumber":29,"author":{"gitId":"kevinkuo0320"},"content":"    }","lastModifiedDate":"2022-01-20"},{"lineNumber":30,"author":{"gitId":"kevinkuo0320"},"content":"","lastModifiedDate":"2022-01-20"},{"lineNumber":31,"author":{"gitId":"kevinkuo0320"},"content":"","lastModifiedDate":"2022-01-20"},{"lineNumber":32,"author":{"gitId":"kevinkuo0320"},"content":"","lastModifiedDate":"2022-01-20"},{"lineNumber":33,"author":{"gitId":"kevinkuo0320"},"content":"","lastModifiedDate":"2022-01-20"},{"lineNumber":34,"author":{"gitId":"kevinkuo0320"},"content":"}","lastModifiedDate":"2022-01-20"}],"authorContributionMap":{"kevinkuo0320":34}},{"path":"src/main/java/Todo.java","fileType":"java","lines":[{"lineNumber":1,"author":{"gitId":"kevinkuo0320"},"content":"public class Todo  extends Task{","lastModifiedDate":"2022-01-20"},{"lineNumber":2,"author":{"gitId":"kevinkuo0320"},"content":"    public String tag;","lastModifiedDate":"2022-01-20"},{"lineNumber":3,"author":{"gitId":"kevinkuo0320"},"content":"","lastModifiedDate":"2022-01-20"},{"lineNumber":4,"author":{"gitId":"kevinkuo0320"},"content":"    public Todo(String description){","lastModifiedDate":"2022-01-20"},{"lineNumber":5,"author":{"gitId":"kevinkuo0320"},"content":"        super(description, \"T\");","lastModifiedDate":"2022-01-20"},{"lineNumber":6,"author":{"gitId":"kevinkuo0320"},"content":"        this.tag \u003d \"T\";","lastModifiedDate":"2022-01-20"},{"lineNumber":7,"author":{"gitId":"kevinkuo0320"},"content":"    }","lastModifiedDate":"2022-01-20"},{"lineNumber":8,"author":{"gitId":"kevinkuo0320"},"content":"","lastModifiedDate":"2022-01-20"},{"lineNumber":9,"author":{"gitId":"kevinkuo0320"},"content":"    public String getTag(){","lastModifiedDate":"2022-01-20"},{"lineNumber":10,"author":{"gitId":"kevinkuo0320"},"content":"        return \"[\" + tag + \"]\";","lastModifiedDate":"2022-01-20"},{"lineNumber":11,"author":{"gitId":"kevinkuo0320"},"content":"    }","lastModifiedDate":"2022-01-20"},{"lineNumber":12,"author":{"gitId":"kevinkuo0320"},"content":"}","lastModifiedDate":"2022-01-20"}],"authorContributionMap":{"kevinkuo0320":12}}]
