[{"path":"src/main/java/Duke.java","fileType":"java","lines":[{"lineNumber":1,"author":{"gitId":"fantablack"},"content":"import java.util.ArrayList;","lastModifiedDate":"2022-01-20"},{"lineNumber":2,"author":{"gitId":"fantablack"},"content":"import java.util.Scanner;","lastModifiedDate":"2022-01-20"},{"lineNumber":3,"author":{"gitId":"fantablack"},"content":"","lastModifiedDate":"2022-01-20"},{"lineNumber":4,"author":{"gitId":"-"},"content":"public class Duke {","lastModifiedDate":"2019-07-29"},{"lineNumber":5,"author":{"gitId":"-"},"content":"    public static void main(String[] args) {","lastModifiedDate":"2019-07-29"},{"lineNumber":6,"author":{"gitId":"fantablack"},"content":"        Scanner sc \u003d new Scanner(System.in);","lastModifiedDate":"2022-01-20"},{"lineNumber":7,"author":{"gitId":"fantablack"},"content":"","lastModifiedDate":"2022-01-20"},{"lineNumber":8,"author":{"gitId":"fantablack"},"content":"        String greeting \u003d \"Hello! I\u0027m Kizer\\nWhat can I do for you?\";","lastModifiedDate":"2022-01-20"},{"lineNumber":9,"author":{"gitId":"fantablack"},"content":"        String bar \u003d \"____________________________________________________________\";","lastModifiedDate":"2022-01-20"},{"lineNumber":10,"author":{"gitId":"fantablack"},"content":"        System.out.println(bar);","lastModifiedDate":"2022-01-20"},{"lineNumber":11,"author":{"gitId":"fantablack"},"content":"        System.out.println(greeting);","lastModifiedDate":"2022-01-20"},{"lineNumber":12,"author":{"gitId":"fantablack"},"content":"        System.out.println(bar);","lastModifiedDate":"2022-01-20"},{"lineNumber":13,"author":{"gitId":"fantablack"},"content":"        ArrayList\u003cTask\u003e taskList \u003d new ArrayList\u003c\u003e();","lastModifiedDate":"2022-01-20"},{"lineNumber":14,"author":{"gitId":"fantablack"},"content":"","lastModifiedDate":"2022-01-20"},{"lineNumber":15,"author":{"gitId":"fantablack"},"content":"        while (true) {","lastModifiedDate":"2022-01-20"},{"lineNumber":16,"author":{"gitId":"fantablack"},"content":"            String input \u003d sc.nextLine();","lastModifiedDate":"2022-01-20"},{"lineNumber":17,"author":{"gitId":"fantablack"},"content":"            if (input.matches(\".*\\\\bbye\\\\b.*\")) {","lastModifiedDate":"2022-01-20"},{"lineNumber":18,"author":{"gitId":"fantablack"},"content":"                System.out.println(bar);","lastModifiedDate":"2022-01-20"},{"lineNumber":19,"author":{"gitId":"fantablack"},"content":"                System.out.println(\"Bye. Hope to see you again soon!\");","lastModifiedDate":"2022-01-20"},{"lineNumber":20,"author":{"gitId":"fantablack"},"content":"                System.out.println(bar);","lastModifiedDate":"2022-01-20"},{"lineNumber":21,"author":{"gitId":"fantablack"},"content":"                sc.close();","lastModifiedDate":"2022-01-20"},{"lineNumber":22,"author":{"gitId":"fantablack"},"content":"                break;","lastModifiedDate":"2022-01-20"},{"lineNumber":23,"author":{"gitId":"fantablack"},"content":"            } else if (input.matches(\".*\\\\blist\\\\b.*\")) {","lastModifiedDate":"2022-01-20"},{"lineNumber":24,"author":{"gitId":"fantablack"},"content":"                System.out.println(bar);","lastModifiedDate":"2022-01-20"},{"lineNumber":25,"author":{"gitId":"fantablack"},"content":"                System.out.println(\"Here are the tasks in your list:\");","lastModifiedDate":"2022-01-20"},{"lineNumber":26,"author":{"gitId":"fantablack"},"content":"                for (int i \u003d 1; i \u003c\u003d taskList.size(); i++) {","lastModifiedDate":"2022-01-20"},{"lineNumber":27,"author":{"gitId":"fantablack"},"content":"                    Task curr \u003d taskList.get(i - 1);","lastModifiedDate":"2022-01-20"},{"lineNumber":28,"author":{"gitId":"fantablack"},"content":"                    System.out.println(i + \".\" + \"[\" + curr.getStatusIcon() + \"] \" + curr);","lastModifiedDate":"2022-01-20"},{"lineNumber":29,"author":{"gitId":"fantablack"},"content":"                }","lastModifiedDate":"2022-01-20"},{"lineNumber":30,"author":{"gitId":"fantablack"},"content":"                System.out.println(bar);","lastModifiedDate":"2022-01-20"},{"lineNumber":31,"author":{"gitId":"fantablack"},"content":"            } else if (input.matches(\".*\\\\bmark\\\\b.*\")) {","lastModifiedDate":"2022-01-20"},{"lineNumber":32,"author":{"gitId":"fantablack"},"content":"                String numberOnly \u003d input.replaceAll(\"[^0-9]\", \"\");","lastModifiedDate":"2022-01-20"},{"lineNumber":33,"author":{"gitId":"fantablack"},"content":"                int number \u003d Integer.parseInt(numberOnly);","lastModifiedDate":"2022-01-20"},{"lineNumber":34,"author":{"gitId":"fantablack"},"content":"                Task curr \u003d taskList.get(number - 1);","lastModifiedDate":"2022-01-20"},{"lineNumber":35,"author":{"gitId":"fantablack"},"content":"","lastModifiedDate":"2022-01-20"},{"lineNumber":36,"author":{"gitId":"fantablack"},"content":"                curr.markAsDone();","lastModifiedDate":"2022-01-20"},{"lineNumber":37,"author":{"gitId":"fantablack"},"content":"                System.out.println(bar);","lastModifiedDate":"2022-01-20"},{"lineNumber":38,"author":{"gitId":"fantablack"},"content":"                System.out.println(\"Nice! I\u0027ve marked this task as done:\");","lastModifiedDate":"2022-01-20"},{"lineNumber":39,"author":{"gitId":"fantablack"},"content":"                System.out.println(\"[\" + curr.getStatusIcon() + \"] \" + curr);","lastModifiedDate":"2022-01-20"},{"lineNumber":40,"author":{"gitId":"fantablack"},"content":"                System.out.println(bar);","lastModifiedDate":"2022-01-20"},{"lineNumber":41,"author":{"gitId":"fantablack"},"content":"","lastModifiedDate":"2022-01-20"},{"lineNumber":42,"author":{"gitId":"fantablack"},"content":"            } else if (input.matches(\".*\\\\bunmark\\\\b.*\")) {","lastModifiedDate":"2022-01-20"},{"lineNumber":43,"author":{"gitId":"fantablack"},"content":"                String numberOnly \u003d input.replaceAll(\"[^0-9]\", \"\");","lastModifiedDate":"2022-01-20"},{"lineNumber":44,"author":{"gitId":"fantablack"},"content":"                int number \u003d Integer.parseInt(numberOnly);","lastModifiedDate":"2022-01-20"},{"lineNumber":45,"author":{"gitId":"fantablack"},"content":"                Task curr \u003d taskList.get(number - 1);","lastModifiedDate":"2022-01-20"},{"lineNumber":46,"author":{"gitId":"fantablack"},"content":"","lastModifiedDate":"2022-01-20"},{"lineNumber":47,"author":{"gitId":"fantablack"},"content":"                curr.markAsUndone();","lastModifiedDate":"2022-01-20"},{"lineNumber":48,"author":{"gitId":"fantablack"},"content":"                System.out.println(bar);","lastModifiedDate":"2022-01-20"},{"lineNumber":49,"author":{"gitId":"fantablack"},"content":"                System.out.println(\"OK, I\u0027ve marked this task as not done yet:\");","lastModifiedDate":"2022-01-20"},{"lineNumber":50,"author":{"gitId":"fantablack"},"content":"                System.out.println(\"[\" + curr.getStatusIcon() + \"] \" + curr);","lastModifiedDate":"2022-01-20"},{"lineNumber":51,"author":{"gitId":"fantablack"},"content":"                System.out.println(bar);","lastModifiedDate":"2022-01-20"},{"lineNumber":52,"author":{"gitId":"fantablack"},"content":"            } else {","lastModifiedDate":"2022-01-20"},{"lineNumber":53,"author":{"gitId":"fantablack"},"content":"                System.out.println(bar);","lastModifiedDate":"2022-01-20"},{"lineNumber":54,"author":{"gitId":"fantablack"},"content":"                Task curr \u003d new Task(input);","lastModifiedDate":"2022-01-20"},{"lineNumber":55,"author":{"gitId":"fantablack"},"content":"                taskList.add(curr);","lastModifiedDate":"2022-01-20"},{"lineNumber":56,"author":{"gitId":"fantablack"},"content":"                System.out.println(\"added: \" + curr);","lastModifiedDate":"2022-01-20"},{"lineNumber":57,"author":{"gitId":"fantablack"},"content":"                System.out.println(bar);","lastModifiedDate":"2022-01-20"},{"lineNumber":58,"author":{"gitId":"fantablack"},"content":"            }","lastModifiedDate":"2022-01-20"},{"lineNumber":59,"author":{"gitId":"fantablack"},"content":"","lastModifiedDate":"2022-01-20"},{"lineNumber":60,"author":{"gitId":"fantablack"},"content":"        }","lastModifiedDate":"2022-01-20"},{"lineNumber":61,"author":{"gitId":"fantablack"},"content":"","lastModifiedDate":"2022-01-20"},{"lineNumber":62,"author":{"gitId":"-"},"content":"    }","lastModifiedDate":"2019-07-29"},{"lineNumber":63,"author":{"gitId":"-"},"content":"}","lastModifiedDate":"2019-07-29"}],"authorContributionMap":{"fantablack":59,"-":4}},{"path":"src/main/java/Kattio.java","fileType":"java","lines":[{"lineNumber":1,"author":{"gitId":"fantablack"},"content":"/** Simple yet moderately fast I/O routines.","lastModifiedDate":"2022-01-20"},{"lineNumber":2,"author":{"gitId":"fantablack"},"content":" *","lastModifiedDate":"2022-01-20"},{"lineNumber":3,"author":{"gitId":"fantablack"},"content":" * Example usage:","lastModifiedDate":"2022-01-20"},{"lineNumber":4,"author":{"gitId":"fantablack"},"content":" *","lastModifiedDate":"2022-01-20"},{"lineNumber":5,"author":{"gitId":"fantablack"},"content":" * Kattio io \u003d new Kattio(System.in, System.out);","lastModifiedDate":"2022-01-20"},{"lineNumber":6,"author":{"gitId":"fantablack"},"content":" *","lastModifiedDate":"2022-01-20"},{"lineNumber":7,"author":{"gitId":"fantablack"},"content":" * while (io.hasMoreTokens()) {","lastModifiedDate":"2022-01-20"},{"lineNumber":8,"author":{"gitId":"fantablack"},"content":" *    int n \u003d io.getInt();","lastModifiedDate":"2022-01-20"},{"lineNumber":9,"author":{"gitId":"fantablack"},"content":" *    double d \u003d io.getDouble();","lastModifiedDate":"2022-01-20"},{"lineNumber":10,"author":{"gitId":"fantablack"},"content":" *    double ans \u003d d*n;","lastModifiedDate":"2022-01-20"},{"lineNumber":11,"author":{"gitId":"fantablack"},"content":" *","lastModifiedDate":"2022-01-20"},{"lineNumber":12,"author":{"gitId":"fantablack"},"content":" *    io.println(\"Answer: \" + ans);","lastModifiedDate":"2022-01-20"},{"lineNumber":13,"author":{"gitId":"fantablack"},"content":" * }","lastModifiedDate":"2022-01-20"},{"lineNumber":14,"author":{"gitId":"fantablack"},"content":" *","lastModifiedDate":"2022-01-20"},{"lineNumber":15,"author":{"gitId":"fantablack"},"content":" * io.close();","lastModifiedDate":"2022-01-20"},{"lineNumber":16,"author":{"gitId":"fantablack"},"content":" *","lastModifiedDate":"2022-01-20"},{"lineNumber":17,"author":{"gitId":"fantablack"},"content":" *","lastModifiedDate":"2022-01-20"},{"lineNumber":18,"author":{"gitId":"fantablack"},"content":" * Some notes:","lastModifiedDate":"2022-01-20"},{"lineNumber":19,"author":{"gitId":"fantablack"},"content":" *","lastModifiedDate":"2022-01-20"},{"lineNumber":20,"author":{"gitId":"fantablack"},"content":" * - When done, you should always do io.close() or io.flush() on the","lastModifiedDate":"2022-01-20"},{"lineNumber":21,"author":{"gitId":"fantablack"},"content":" *   Kattio-instance, otherwise, you may lose output.","lastModifiedDate":"2022-01-20"},{"lineNumber":22,"author":{"gitId":"fantablack"},"content":" *","lastModifiedDate":"2022-01-20"},{"lineNumber":23,"author":{"gitId":"fantablack"},"content":" * - The getInt(), getDouble(), and getLong() methods will throw an","lastModifiedDate":"2022-01-20"},{"lineNumber":24,"author":{"gitId":"fantablack"},"content":" *   exception if there is no more data in the input, so it is generally","lastModifiedDate":"2022-01-20"},{"lineNumber":25,"author":{"gitId":"fantablack"},"content":" *   a good idea to use hasMoreTokens() to check for end-of-file.","lastModifiedDate":"2022-01-20"},{"lineNumber":26,"author":{"gitId":"fantablack"},"content":" *","lastModifiedDate":"2022-01-20"},{"lineNumber":27,"author":{"gitId":"fantablack"},"content":" * @author: Kattis","lastModifiedDate":"2022-01-20"},{"lineNumber":28,"author":{"gitId":"fantablack"},"content":" */","lastModifiedDate":"2022-01-20"},{"lineNumber":29,"author":{"gitId":"fantablack"},"content":"","lastModifiedDate":"2022-01-20"},{"lineNumber":30,"author":{"gitId":"fantablack"},"content":"import java.util.StringTokenizer;","lastModifiedDate":"2022-01-20"},{"lineNumber":31,"author":{"gitId":"fantablack"},"content":"import java.io.BufferedReader;","lastModifiedDate":"2022-01-20"},{"lineNumber":32,"author":{"gitId":"fantablack"},"content":"import java.io.BufferedOutputStream;","lastModifiedDate":"2022-01-20"},{"lineNumber":33,"author":{"gitId":"fantablack"},"content":"import java.io.IOException;","lastModifiedDate":"2022-01-20"},{"lineNumber":34,"author":{"gitId":"fantablack"},"content":"import java.io.InputStream;","lastModifiedDate":"2022-01-20"},{"lineNumber":35,"author":{"gitId":"fantablack"},"content":"import java.io.InputStreamReader;","lastModifiedDate":"2022-01-20"},{"lineNumber":36,"author":{"gitId":"fantablack"},"content":"import java.io.PrintWriter;","lastModifiedDate":"2022-01-20"},{"lineNumber":37,"author":{"gitId":"fantablack"},"content":"import java.io.OutputStream;","lastModifiedDate":"2022-01-20"},{"lineNumber":38,"author":{"gitId":"fantablack"},"content":"","lastModifiedDate":"2022-01-20"},{"lineNumber":39,"author":{"gitId":"fantablack"},"content":"class Kattio extends PrintWriter {","lastModifiedDate":"2022-01-20"},{"lineNumber":40,"author":{"gitId":"fantablack"},"content":"    public Kattio(InputStream i) {","lastModifiedDate":"2022-01-20"},{"lineNumber":41,"author":{"gitId":"fantablack"},"content":"        super(new BufferedOutputStream(System.out));","lastModifiedDate":"2022-01-20"},{"lineNumber":42,"author":{"gitId":"fantablack"},"content":"        r \u003d new BufferedReader(new InputStreamReader(i));","lastModifiedDate":"2022-01-20"},{"lineNumber":43,"author":{"gitId":"fantablack"},"content":"    }","lastModifiedDate":"2022-01-20"},{"lineNumber":44,"author":{"gitId":"fantablack"},"content":"    public Kattio(InputStream i, OutputStream o) {","lastModifiedDate":"2022-01-20"},{"lineNumber":45,"author":{"gitId":"fantablack"},"content":"        super(new BufferedOutputStream(o));","lastModifiedDate":"2022-01-20"},{"lineNumber":46,"author":{"gitId":"fantablack"},"content":"        r \u003d new BufferedReader(new InputStreamReader(i));","lastModifiedDate":"2022-01-20"},{"lineNumber":47,"author":{"gitId":"fantablack"},"content":"    }","lastModifiedDate":"2022-01-20"},{"lineNumber":48,"author":{"gitId":"fantablack"},"content":"","lastModifiedDate":"2022-01-20"},{"lineNumber":49,"author":{"gitId":"fantablack"},"content":"    public boolean hasMoreTokens() {","lastModifiedDate":"2022-01-20"},{"lineNumber":50,"author":{"gitId":"fantablack"},"content":"        return peekToken() !\u003d null;","lastModifiedDate":"2022-01-20"},{"lineNumber":51,"author":{"gitId":"fantablack"},"content":"    }","lastModifiedDate":"2022-01-20"},{"lineNumber":52,"author":{"gitId":"fantablack"},"content":"","lastModifiedDate":"2022-01-20"},{"lineNumber":53,"author":{"gitId":"fantablack"},"content":"    public int getInt() {","lastModifiedDate":"2022-01-20"},{"lineNumber":54,"author":{"gitId":"fantablack"},"content":"        return Integer.parseInt(nextToken());","lastModifiedDate":"2022-01-20"},{"lineNumber":55,"author":{"gitId":"fantablack"},"content":"    }","lastModifiedDate":"2022-01-20"},{"lineNumber":56,"author":{"gitId":"fantablack"},"content":"","lastModifiedDate":"2022-01-20"},{"lineNumber":57,"author":{"gitId":"fantablack"},"content":"    public double getDouble() {","lastModifiedDate":"2022-01-20"},{"lineNumber":58,"author":{"gitId":"fantablack"},"content":"        return Double.parseDouble(nextToken());","lastModifiedDate":"2022-01-20"},{"lineNumber":59,"author":{"gitId":"fantablack"},"content":"    }","lastModifiedDate":"2022-01-20"},{"lineNumber":60,"author":{"gitId":"fantablack"},"content":"","lastModifiedDate":"2022-01-20"},{"lineNumber":61,"author":{"gitId":"fantablack"},"content":"    public long getLong() {","lastModifiedDate":"2022-01-20"},{"lineNumber":62,"author":{"gitId":"fantablack"},"content":"        return Long.parseLong(nextToken());","lastModifiedDate":"2022-01-20"},{"lineNumber":63,"author":{"gitId":"fantablack"},"content":"    }","lastModifiedDate":"2022-01-20"},{"lineNumber":64,"author":{"gitId":"fantablack"},"content":"","lastModifiedDate":"2022-01-20"},{"lineNumber":65,"author":{"gitId":"fantablack"},"content":"    public String getWord() {","lastModifiedDate":"2022-01-20"},{"lineNumber":66,"author":{"gitId":"fantablack"},"content":"        return nextToken();","lastModifiedDate":"2022-01-20"},{"lineNumber":67,"author":{"gitId":"fantablack"},"content":"    }","lastModifiedDate":"2022-01-20"},{"lineNumber":68,"author":{"gitId":"fantablack"},"content":"","lastModifiedDate":"2022-01-20"},{"lineNumber":69,"author":{"gitId":"fantablack"},"content":"","lastModifiedDate":"2022-01-20"},{"lineNumber":70,"author":{"gitId":"fantablack"},"content":"","lastModifiedDate":"2022-01-20"},{"lineNumber":71,"author":{"gitId":"fantablack"},"content":"    private BufferedReader r;","lastModifiedDate":"2022-01-20"},{"lineNumber":72,"author":{"gitId":"fantablack"},"content":"    private String line;","lastModifiedDate":"2022-01-20"},{"lineNumber":73,"author":{"gitId":"fantablack"},"content":"    private StringTokenizer st;","lastModifiedDate":"2022-01-20"},{"lineNumber":74,"author":{"gitId":"fantablack"},"content":"    private String token;","lastModifiedDate":"2022-01-20"},{"lineNumber":75,"author":{"gitId":"fantablack"},"content":"","lastModifiedDate":"2022-01-20"},{"lineNumber":76,"author":{"gitId":"fantablack"},"content":"    private String peekToken() {","lastModifiedDate":"2022-01-20"},{"lineNumber":77,"author":{"gitId":"fantablack"},"content":"        if (token \u003d\u003d null)","lastModifiedDate":"2022-01-20"},{"lineNumber":78,"author":{"gitId":"fantablack"},"content":"            try {","lastModifiedDate":"2022-01-20"},{"lineNumber":79,"author":{"gitId":"fantablack"},"content":"                while (st \u003d\u003d null || !st.hasMoreTokens()) {","lastModifiedDate":"2022-01-20"},{"lineNumber":80,"author":{"gitId":"fantablack"},"content":"                    line \u003d r.readLine();","lastModifiedDate":"2022-01-20"},{"lineNumber":81,"author":{"gitId":"fantablack"},"content":"                    if (line \u003d\u003d null) return null;","lastModifiedDate":"2022-01-20"},{"lineNumber":82,"author":{"gitId":"fantablack"},"content":"                    st \u003d new StringTokenizer(line); //the \"\u003d,;\" is to include whitespace","lastModifiedDate":"2022-01-20"},{"lineNumber":83,"author":{"gitId":"fantablack"},"content":"                }","lastModifiedDate":"2022-01-20"},{"lineNumber":84,"author":{"gitId":"fantablack"},"content":"                token \u003d st.nextToken();","lastModifiedDate":"2022-01-20"},{"lineNumber":85,"author":{"gitId":"fantablack"},"content":"            } catch (IOException e) { }","lastModifiedDate":"2022-01-20"},{"lineNumber":86,"author":{"gitId":"fantablack"},"content":"        return token;","lastModifiedDate":"2022-01-20"},{"lineNumber":87,"author":{"gitId":"fantablack"},"content":"    }","lastModifiedDate":"2022-01-20"},{"lineNumber":88,"author":{"gitId":"fantablack"},"content":"","lastModifiedDate":"2022-01-20"},{"lineNumber":89,"author":{"gitId":"fantablack"},"content":"    private String nextToken() {","lastModifiedDate":"2022-01-20"},{"lineNumber":90,"author":{"gitId":"fantablack"},"content":"        String ans \u003d peekToken();","lastModifiedDate":"2022-01-20"},{"lineNumber":91,"author":{"gitId":"fantablack"},"content":"        token \u003d null;","lastModifiedDate":"2022-01-20"},{"lineNumber":92,"author":{"gitId":"fantablack"},"content":"        return ans;","lastModifiedDate":"2022-01-20"},{"lineNumber":93,"author":{"gitId":"fantablack"},"content":"    }","lastModifiedDate":"2022-01-20"},{"lineNumber":94,"author":{"gitId":"fantablack"},"content":"}","lastModifiedDate":"2022-01-20"}],"authorContributionMap":{"fantablack":94}},{"path":"src/main/java/Task.java","fileType":"java","lines":[{"lineNumber":1,"author":{"gitId":"fantablack"},"content":"public class Task {","lastModifiedDate":"2022-01-20"},{"lineNumber":2,"author":{"gitId":"fantablack"},"content":"    protected String description;","lastModifiedDate":"2022-01-20"},{"lineNumber":3,"author":{"gitId":"fantablack"},"content":"    protected boolean isDone;","lastModifiedDate":"2022-01-20"},{"lineNumber":4,"author":{"gitId":"fantablack"},"content":"","lastModifiedDate":"2022-01-20"},{"lineNumber":5,"author":{"gitId":"fantablack"},"content":"    public Task(String description) {","lastModifiedDate":"2022-01-20"},{"lineNumber":6,"author":{"gitId":"fantablack"},"content":"        this.description \u003d description;","lastModifiedDate":"2022-01-20"},{"lineNumber":7,"author":{"gitId":"fantablack"},"content":"        this.isDone \u003d false;","lastModifiedDate":"2022-01-20"},{"lineNumber":8,"author":{"gitId":"fantablack"},"content":"    }","lastModifiedDate":"2022-01-20"},{"lineNumber":9,"author":{"gitId":"fantablack"},"content":"","lastModifiedDate":"2022-01-20"},{"lineNumber":10,"author":{"gitId":"fantablack"},"content":"    public String getStatusIcon() {","lastModifiedDate":"2022-01-20"},{"lineNumber":11,"author":{"gitId":"fantablack"},"content":"        return (isDone ? \"X\" : \" \"); // mark done task with X","lastModifiedDate":"2022-01-20"},{"lineNumber":12,"author":{"gitId":"fantablack"},"content":"    }","lastModifiedDate":"2022-01-20"},{"lineNumber":13,"author":{"gitId":"fantablack"},"content":"","lastModifiedDate":"2022-01-20"},{"lineNumber":14,"author":{"gitId":"fantablack"},"content":"    public String getDescription() {","lastModifiedDate":"2022-01-20"},{"lineNumber":15,"author":{"gitId":"fantablack"},"content":"        return description;","lastModifiedDate":"2022-01-20"},{"lineNumber":16,"author":{"gitId":"fantablack"},"content":"    }","lastModifiedDate":"2022-01-20"},{"lineNumber":17,"author":{"gitId":"fantablack"},"content":"","lastModifiedDate":"2022-01-20"},{"lineNumber":18,"author":{"gitId":"fantablack"},"content":"    public String markAsDone() {","lastModifiedDate":"2022-01-20"},{"lineNumber":19,"author":{"gitId":"fantablack"},"content":"        this.isDone \u003d true;","lastModifiedDate":"2022-01-20"},{"lineNumber":20,"author":{"gitId":"fantablack"},"content":"        return this.description + \" is done!\";","lastModifiedDate":"2022-01-20"},{"lineNumber":21,"author":{"gitId":"fantablack"},"content":"    }","lastModifiedDate":"2022-01-20"},{"lineNumber":22,"author":{"gitId":"fantablack"},"content":"","lastModifiedDate":"2022-01-20"},{"lineNumber":23,"author":{"gitId":"fantablack"},"content":"    public String markAsUndone() {","lastModifiedDate":"2022-01-20"},{"lineNumber":24,"author":{"gitId":"fantablack"},"content":"        this.isDone \u003d false;","lastModifiedDate":"2022-01-20"},{"lineNumber":25,"author":{"gitId":"fantablack"},"content":"        return this.description + \" is undone!\";","lastModifiedDate":"2022-01-20"},{"lineNumber":26,"author":{"gitId":"fantablack"},"content":"    }","lastModifiedDate":"2022-01-20"},{"lineNumber":27,"author":{"gitId":"fantablack"},"content":"","lastModifiedDate":"2022-01-20"},{"lineNumber":28,"author":{"gitId":"fantablack"},"content":"    @Override","lastModifiedDate":"2022-01-20"},{"lineNumber":29,"author":{"gitId":"fantablack"},"content":"    public String toString() {","lastModifiedDate":"2022-01-20"},{"lineNumber":30,"author":{"gitId":"fantablack"},"content":"        // TODO Auto-generated method stub","lastModifiedDate":"2022-01-20"},{"lineNumber":31,"author":{"gitId":"fantablack"},"content":"        return this.description;","lastModifiedDate":"2022-01-20"},{"lineNumber":32,"author":{"gitId":"fantablack"},"content":"    }","lastModifiedDate":"2022-01-20"},{"lineNumber":33,"author":{"gitId":"fantablack"},"content":"}","lastModifiedDate":"2022-01-20"}],"authorContributionMap":{"fantablack":33}}]
