{"authorDailyContributionsMap":{"Spyobird":[{"date":"2022-01-18","commitResults":[{"hash":"bc541b0bbf3e17ee93b5bfb449d883056eefd660","messageTitle":"Rename Duke.java to Juke.java; add greet, echo and exit functionality to Juke.java","messageBody":"","tags":["Level-1"],"fileTypesAndContributionMap":{"java":{"insertions":54,"deletions":10}}}]}]},"authorFileTypeContributionMap":{"Spyobird":{"java":54,"md":0,"fxml":0,"sh":0,"bat":0,"gradle":0,"txt":0}},"authorContributionVariance":{"Spyobird":655.36},"authorDisplayNameMap":{"Spyobird":"ELLI..YONG"}}
